BayesIA/Redes.py
BayesIA/__init__.py
BayesIA-0.0.13.dist-info/METADATA
BayesIA-0.0.13.dist-info/WHEEL
BayesIA-0.0.13.dist-info/top_level.txt
BayesIA-0.0.13.dist-info/RECORD
