Metadata-Version: 2.1
Name: BayesIA
Version: 0.0.13
Summary: redes bayesianas
Home-page: UNKNOWN
Author: riv19062
Author-email: <eleanjulian@gmail.com>
License: UNKNOWN
Keywords: python,IA,bayes
Platform: UNKNOWN
Classifier: Development Status :: 1 - Planning
Classifier: Intended Audience :: Developers
Classifier: Programming Language :: Python :: 3
Classifier: Operating System :: Unix
Classifier: Operating System :: MacOS :: MacOS X
Classifier: Operating System :: Microsoft :: Windows
Requires-Dist: networkx
